kahipwrapper-0.1.7.dist-info/WHEEL
kahipwrapper-0.1.7.dist-info/RECORD
kahipwrapper-0.1.7.dist-info/metadata.json
kahipwrapper-0.1.7.dist-info/DESCRIPTION.rst
kahipwrapper-0.1.7.dist-info/top_level.txt
kahipwrapper-0.1.7.dist-info/METADATA
kahipwrapper/__init__.py
kahipwrapper/kaHIP.py
kahipwrapper/_kaHIP.so
kahipwrapper/test.py
kahipwrapper/.libs/libgomp-3300acd3.so.1.0.0
