Metadata-Version: 2.0
Name: kahipwrapper
Version: 0.1.7
Summary: KaHIP Python Wrapper
Home-page: http://github.com/suriyan/KaHIP-wrapper
Author: Suriyan Lahaprapanon, Gaurav Sood
Author-email: suriyant@gmail.com, gsood07@gmail.com
License: MIT
Platform: UNKNOWN
